LICENSE
README.md
setup.py
CVE_2023_4568.egg-info/PKG-INFO
CVE_2023_4568.egg-info/SOURCES.txt
CVE_2023_4568.egg-info/dependency_links.txt
CVE_2023_4568.egg-info/entry_points.txt
CVE_2023_4568.egg-info/requires.txt
CVE_2023_4568.egg-info/top_level.txt
cve20234568/__init__.py
cve20234568/main.py
cve20234568/includes/__init__.py
cve20234568/includes/bot.py
cve20234568/includes/filereader.py
cve20234568/includes/scan.py
cve20234568/includes/writefile.py
cve20234568/utils/__init__.py
cve20234568/utils/configure.py
cve20234568/utils/const.py
cve20234568/utils/helpers.py
cve20234568/utils/status.py